lastipy/__init__.py
lastipy/definitions.py
lastipy/track.py
lastipy/lastfm/__init__.py
lastipy/lastfm/lastfm_recommendations.py
lastipy/lastfm/parse_lastfm_tracks.py
lastipy/lastfm/library/__init__.py
lastipy/lastfm/library/paginated_endpoint.py
lastipy/lastfm/library/period.py
lastipy/lastfm/library/recent_artists.py
lastipy/lastfm/library/recent_tracks.py
lastipy/lastfm/library/scrobbled_artist.py
lastipy/lastfm/library/top_track.py
lastipy/lastfm/library/top_tracks.py
lastipy/lastfm/library/track_info.py
lastipy/recommendations/__init__.py
lastipy/recommendations/rating_calculator.py
lastipy/recommendations/recommendations.py
lastipy/recommendations/recommended_track.py
lastipy/spotify/__init__.py
lastipy/spotify/album.py
lastipy/spotify/library.py
lastipy/spotify/new_releases.py
lastipy/spotify/parse_spotify_tracks.py
lastipy/spotify/playlist.py
lastipy/spotify/playlist_track.py
lastipy/spotify/search.py
lastipy/spotify/spotify_recommendations.py
lastipy/spotify/token.py
lastipy/util/__init__.py
lastipy/util/chunk.py
lastipy/util/filter.py
lastipy/util/parse_api_keys.py
lastipy/util/setup_logging.py
scripts/__init__.py
scripts/organize_favorites.py
scripts/recommendations_playlist.py
scripts/save_new_releases.py
test/__init__.py
test/test_requests.py
test/lastfm/__init__.py
test/lastfm/test_lastfm_recommendations.py
test/lastfm/test_parse_lastfm_tracks.py
test/lastfm/library/__init__.py
test/lastfm/library/test_fetch_playcount.py
test/lastfm/library/test_paginated_endpoint.py
test/lastfm/library/test_recent_artists.py
test/lastfm/library/test_recent_tracks.py
test/lastfm/library/test_top_tracks.py
test/recommendations/__init__.py
test/recommendations/test_generate_recommendations.py
test/recommendations/test_rating_calculator.py
test/spotify/__init__.py
test/spotify/test_add_albums_to_library.py
test/spotify/test_add_tracks_to_library.py
test/spotify/test_get_saved_tracks.py
lastipy-1.1.43.dist-info/METADATA
lastipy-1.1.43.dist-info/WHEEL
lastipy-1.1.43.dist-info/entry_points.txt
lastipy-1.1.43.dist-info/top_level.txt
lastipy-1.1.43.dist-info/RECORD
